pydownloadfile/__init__.py
pydownloadfile/pydownloadfile.py
pydownloadfile-0.5.dist-info/LICENSE
pydownloadfile-0.5.dist-info/METADATA
pydownloadfile-0.5.dist-info/WHEEL
pydownloadfile-0.5.dist-info/top_level.txt
pydownloadfile-0.5.dist-info/RECORD
